Metadata-Version: 1.1
Name: tapp-config
Version: 0.0.2
Summary: Configuration for tapps (redis, logger, etc.)
Home-page: https://github.com/gitguild/tapp-config
Author: Ira Miller
Author-email: ira@gitguild.com
License: MIT
Platform: UNKNOWN
Classifier: License :: OSI Approved :: MIT License
Classifier: Programming Language :: Python :: 2
Classifier: Programming Language :: Python :: 3
Classifier: Topic :: Software Development :: Libraries
